aerapi/__init__.py
aerapi/common/__init__.py
aerapi/common/api_config.py
aerapi/common/base_api.py
aerapi/common/utils.py
aerapi/external/__init__.py
aerapi/external/api_client.py
aerapi/external/external_utils.py
aerapi/internal/__init__.py
aerapi/internal/api_client.py
aerapi/internal/internal_utils.py
aerapi-0.2.3.dist-info/METADATA
aerapi-0.2.3.dist-info/WHEEL
aerapi-0.2.3.dist-info/top_level.txt
aerapi-0.2.3.dist-info/RECORD
