Metadata-Version: 2.1
Name: aerapi
Version: 0.2.3
Summary: A comprehensive toolset for accessing REST APIs used by the data team
Author: S.Nicholson
Author-email: sean.nicholson@aerlytix.com
Classifier: Programming Language :: Python :: 3
Classifier: License :: OSI Approved :: MIT License
Classifier: Operating System :: OS Independent
Requires-Python: >=3.6
Requires-Dist: deepdiff
Requires-Dist: numpy
Requires-Dist: pandas
Requires-Dist: PyYAML
Requires-Dist: requests
